captn_nanobit_client/__init__.py
captn_nanobit_client/_nbdev.py
captn_nanobit_client/api.py
captn_nanobit_client/plotly_graph.py
captn_nanobit_client/testing.py
captn_nanobit_client-0.0.10.dist-info/LICENSE
captn_nanobit_client-0.0.10.dist-info/METADATA
captn_nanobit_client-0.0.10.dist-info/WHEEL
captn_nanobit_client-0.0.10.dist-info/entry_points.txt
captn_nanobit_client-0.0.10.dist-info/top_level.txt
captn_nanobit_client-0.0.10.dist-info/RECORD
