Metadata-Version: 2.1
Name: captn-nanobit-client
Version: 0.0.10
Summary: Project for captn-nanobit client
Home-page: https://gitlab.com/airt.ai/captn/captn-nanobit-client/tree/master/
Author: Capt'n AI
Author-email: info@captn.ai
License: Apache Software License 2.0
Keywords: captn,nanobit,airt,airt.ai
Platform: UNKNOWN
Classifier: Development Status :: 3 - Alpha
Classifier: Intended Audience :: Developers
Classifier: Natural Language :: English
Classifier: Programming Language :: Python :: 3.6
Classifier: Programming Language :: Python :: 3.7
Classifier: Programming Language :: Python :: 3.8
Classifier: License :: OSI Approved :: Apache Software License
Requires-Python: >=3.6
Requires-Dist: pip
Requires-Dist: packaging
Requires-Dist: pandas
Requires-Dist: requests
Requires-Dist: plotly
Requires-Dist: kaleido
Provides-Extra: dev
